k_reg/__init__.py
k_reg/core.py
k_reg_backup_v1_validated/__init__.py
k_reg_backup_v1_validated/core.py
k_reg-2.0.0.dist-info/METADATA
k_reg-2.0.0.dist-info/WHEEL
k_reg-2.0.0.dist-info/top_level.txt
k_reg-2.0.0.dist-info/RECORD
