Metadata-Version: 2.4
Name: k-reg
Version: 2.0.0
Summary: High-performance non-linear K-Regressor (v19, predict=stream).
Home-page: https://github.com/romain/regression-k
Author: Romain
Classifier: Programming Language :: Python :: 3
Classifier: License :: OSI Approved :: MIT License
Classifier: Operating System :: OS Independent
Classifier: Topic :: Scientific/Engineering :: Artificial Intelligence
Requires-Python: >=3.7
Requires-Dist: numpy>=1.19.0
Requires-Dist: scikit-learn>=0.24.0
Requires-Dist: numba>=0.53.0
Dynamic: author
Dynamic: classifier
Dynamic: description
Dynamic: description-content-type
Dynamic: home-page
Dynamic: requires-dist
Dynamic: requires-python
Dynamic: summary
